dPCA/TEP.py
dPCA/__init__.py
dPCA/_modidx.py
dPCA/analysis.py
dPCA/corrmat.py
dPCA/lag.py
dynamicPCA-0.0.3.dist-info/LICENSE
dynamicPCA-0.0.3.dist-info/METADATA
dynamicPCA-0.0.3.dist-info/WHEEL
dynamicPCA-0.0.3.dist-info/entry_points.txt
dynamicPCA-0.0.3.dist-info/top_level.txt
dynamicPCA-0.0.3.dist-info/RECORD
